build/lib/build/lib/build/lib/build/lib/build/lib/build/lib/build/lib/build/lib/build/lib/build/lib/build/lib/build/lib/build/lib/build/lib/build/lib/modm/__init__.py
build/lib/build/lib/build/lib/build/lib/build/lib/build/lib/build/lib/build/lib/build/lib/build/lib/build/lib/build/lib/build/lib/build/lib/build/lib/modm/_zip_utils.py
build/lib/build/lib/build/lib/build/lib/build/lib/build/lib/build/lib/build/lib/build/lib/build/lib/build/lib/build/lib/build/lib/build/lib/build/lib/modm/arm/__init__.py
build/lib/build/lib/build/lib/build/lib/build/lib/build/lib/build/lib/build/lib/build/lib/build/lib/build/lib/build/lib/build/lib/build/lib/build/lib/modm/arm/arm_template.py
build/lib/build/lib/build/lib/build/lib/build/lib/build/lib/build/lib/build/lib/build/lib/build/lib/build/lib/build/lib/build/lib/build/lib/build/lib/modm/arm/arm_template_parameter.py
build/lib/build/lib/build/lib/build/lib/build/lib/build/lib/build/lib/build/lib/build/lib/build/lib/build/lib/build/lib/build/lib/build/lib/build/lib/modm/arm/bicep_template_compiler.py
build/lib/build/lib/build/lib/build/lib/build/lib/build/lib/build/lib/build/lib/build/lib/build/lib/build/lib/build/lib/build/lib/build/lib/build/lib/modm/installer/__init__.py
build/lib/build/lib/build/lib/build/lib/build/lib/build/lib/build/lib/build/lib/build/lib/build/lib/build/lib/build/lib/build/lib/build/lib/build/lib/modm/installer/client_app_package.py
build/lib/build/lib/build/lib/build/lib/build/lib/build/lib/build/lib/build/lib/build/lib/build/lib/build/lib/build/lib/build/lib/build/lib/build/lib/modm/installer/deployment_type.py
build/lib/build/lib/build/lib/build/lib/build/lib/build/lib/build/lib/build/lib/build/lib/build/lib/build/lib/build/lib/build/lib/build/lib/build/lib/modm/installer/installer_package.py
build/lib/build/lib/build/lib/build/lib/build/lib/build/lib/build/lib/build/lib/build/lib/build/lib/build/lib/build/lib/build/lib/build/lib/build/lib/modm/installer/installer_package_result.py
commercial_marketplace_offer_deploy-2.0.2.dist-info/LICENSE
commercial_marketplace_offer_deploy-2.0.2.dist-info/METADATA
commercial_marketplace_offer_deploy-2.0.2.dist-info/WHEEL
commercial_marketplace_offer_deploy-2.0.2.dist-info/top_level.txt
commercial_marketplace_offer_deploy-2.0.2.dist-info/RECORD
