Metadata-Version: 2.1
Name: commercial-marketplace-offer-deploy
Version: 2.0.2
Summary: The Microsoft commercial marketplace app installer packaging SDK
Author-email: Kevin Hillinger <kevin.hillinger@outlook.com>
License: Marketplace Offer Deployment Manager
Project-URL: Homepage, https://github.com/microsoft/commercial-marketplace-offer-deploy
Project-URL: Bug Tracker, https://github.com/microsoft/commercial-marketplace-offer-deploy/issues
Classifier: Programming Language :: Python :: 3
Classifier: Intended Audience :: Developers
Classifier: License :: OSI Approved :: MIT License
Classifier: Operating System :: OS Independent
Requires-Python: >=3.8
License-File: LICENSE
Requires-Dist: python-hcl2 >=4.3.2
Requires-Dist: click ==8.1.7
Requires-Dist: msrest ==0.7.1
Requires-Dist: pybars3 ==0.9.7
Requires-Dist: knack ==0.11.0
Requires-Dist: jsonschema ~=4.19.1
Requires-Dist: jsonschema-specifications ~=2023.7.1
